nonebot_plugin_rikka-0.4.1.dist-info/METADATA
nonebot_plugin_rikka-0.4.1.dist-info/WHEEL
nonebot_plugin_rikka-0.4.1.dist-info/entry_points.txt
nonebot_plugin_rikka-0.4.1.dist-info/licenses/LICENSE
nonebot_plugin_rikka/__init__.py
nonebot_plugin_rikka/alconna.py
nonebot_plugin_rikka/browser.py
nonebot_plugin_rikka/config.py
nonebot_plugin_rikka/constants.py
nonebot_plugin_rikka/database/__init__.py
nonebot_plugin_rikka/database/crud.py
nonebot_plugin_rikka/database/orm_models.py
nonebot_plugin_rikka/extra_proxy.py
nonebot_plugin_rikka/functions/__init__.py
nonebot_plugin_rikka/functions/analysis.py
nonebot_plugin_rikka/functions/fortunate.py
nonebot_plugin_rikka/functions/maistatus.py
nonebot_plugin_rikka/functions/n50.py
nonebot_plugin_rikka/functions/process.py
nonebot_plugin_rikka/functions/recommend_songs.py
nonebot_plugin_rikka/functions/song_tags.py
nonebot_plugin_rikka/migrations/09e00213edc6_add_song_alias_table.py
nonebot_plugin_rikka/migrations/5c791c303fe1_add_maimaipy_identifier.py
nonebot_plugin_rikka/migrations/82115b280b5c_first_revision.py
nonebot_plugin_rikka/migrations/dc59349a578a_add_play_count.py
nonebot_plugin_rikka/migrations/de4344fd6e4c_add_defalut_provider_column.py
nonebot_plugin_rikka/migrations/f273db8f9707_add_song_table.py
nonebot_plugin_rikka/migrations/fb6275585c59_add_divingfish_support.py
nonebot_plugin_rikka/models/song.py
nonebot_plugin_rikka/painters/__init__.py
nonebot_plugin_rikka/painters/_base.py
nonebot_plugin_rikka/painters/_config.py
nonebot_plugin_rikka/painters/analysis.py
nonebot_plugin_rikka/painters/b50.py
nonebot_plugin_rikka/painters/process.py
nonebot_plugin_rikka/painters/score.py
nonebot_plugin_rikka/painters/song.py
nonebot_plugin_rikka/painters/trend.py
nonebot_plugin_rikka/painters/utils.py
nonebot_plugin_rikka/renderer.py
nonebot_plugin_rikka/score/__init__.py
nonebot_plugin_rikka/score/_base.py
nonebot_plugin_rikka/score/_schema.py
nonebot_plugin_rikka/score/providers/diving_fish.py
nonebot_plugin_rikka/score/providers/lxns.py
nonebot_plugin_rikka/score/providers/maimai.py
nonebot_plugin_rikka/updater/__init__.py
nonebot_plugin_rikka/updater/resources.py
nonebot_plugin_rikka/updater/songs.py
nonebot_plugin_rikka-0.4.1.dist-info/RECORD
