Metadata-Version: 2.1
Name: nonebot-plugin-rikka
Version: 0.4.1
Summary: 一个简简单单的舞萌机器人插件
Requires-Python: <4.0,>=3.9
Requires-Dist: nonebot2>=2.4.3
Requires-Dist: nonebot-adapter-onebot>=2.4.6
Requires-Dist: aiohttp>=3.13.1
Requires-Dist: nonebot-plugin-alconna>=0.59.4
Requires-Dist: nonebot-plugin-orm[sqlite]>=0.8.2
Requires-Dist: maimai-py>=1.3.8
Requires-Dist: pillow>=11.3.0
Requires-Dist: playwright>=1.41.0
Requires-Dist: async-lru>=2.0.5
Requires-Dist: numpy<2.4,>=1.26
Requires-Dist: matplotlib>=3.9.4
Requires-Dist: nonebot-plugin-rikka-extra>=0.1.3
Provides-Extra: dev
Requires-Dist: pre-commit>=4.1.0; extra == "dev"
Requires-Dist: mypy>=1.15.0; extra == "dev"
Requires-Dist: black>=25.1.0; extra == "dev"
Requires-Dist: types-PyYAML; extra == "dev"
